sys_info_api/__init__.py
sys_info_api/collectors/bin/arp.py
sys_info_api/common/__init__.py
sys_info_api-0.0.1.dist-info/LICENSE.md
sys_info_api-0.0.1.dist-info/METADATA
sys_info_api-0.0.1.dist-info/WHEEL
sys_info_api-0.0.1.dist-info/top_level.txt
sys_info_api-0.0.1.dist-info/RECORD
