Metadata-Version: 2.1
Name: sys-info-api
Version: 0.0.1
Summary: Collection of APIs to retrieve various system information for Linux, BSD, and MacOS.
Author-email: Charlie Powell <cdp1337@veraciousnetwork.com>
License: # GNU AFFERO GENERAL PUBLIC LICENSE
Project-URL: Homepage, https://github.com/cdp1337/sys-info-api
Project-URL: Issues, https://github.com/cdp1337/sys-info-api/issues
Classifier: Development Status :: 1 - Planning
Classifier: Programming Language :: Python :: 3
Classifier: License :: OSI Approved :: GNU Affero General Public License v3
Classifier: Operating System :: MacOS
Classifier: Operating System :: POSIX :: BSD
Classifier: Operating System :: POSIX :: Linux
Classifier: Intended Audience :: Developers
Classifier: Intended Audience :: Information Technology
Classifier: Intended Audience :: System Administrators
Classifier: Topic :: System :: Filesystems
Classifier: Topic :: System :: Hardware
Classifier: Topic :: System :: Networking
Classifier: Topic :: System :: Operating System
Classifier: Topic :: System :: Systems Administration
Requires-Python: >=3.8
License-File: LICENSE.md
Requires-Dist: python-dateutil >=2.8.2
Requires-Dist: six >=1.16.0
Requires-Dist: ipcalc >=1.99.0
Requires-Dist: requests >=2.31.0
